{
  "Zoo": {
    "max": 0.9524,
    "min": 0
  },
  "Iris": {
    "max": 1,
    "min": 0
  },
  "Wine": {
    "max": 1,
    "min": 0
  },
  "Glass": {
    "max": 0.8837,
    "min": 0
  },
  "Seeds": {
    "max": 0.9524,
    "min": 0
  },
  "Sonar": {
    "max": 0.9048,
    "min": 0
  },
  "Digits": {
    "max": 0.9861,
    "min": 0
  },
  "Monks-1": {
    "max": 1,
    "min": 0
  },
  "Vehicle": {
    "max": 0.8529,
    "min": 0
  },
  "Haberman": {
    "max": 0.7419,
    "min": 0
  },
  "Australian": {
    "max": 0.958,
    "min": 0
  },
  "Ionosphere": {
    "max": 0.9859154929577465,
    "min": 0
  },
  "Balance Scale": {
    "max": 0.95,
    "min": 0
  },
  "Breast Cancer": {
    "max": 0.9825,
    "min": 0
  },
  "Heart Statlog": {
    "max": 0.8704,
    "min": 0
  },
  "Planning Relax": {
    "max": 0.7568,
    "min": 0
  },
  "Liver Disorders": {
    "max": 0.9266144814090019,
    "min": 0
  },
  "Blood Transfusion": {
    "max": 0.8333,
    "min": 0
  },
  "Teaching Assistant": {
    "max": 0.7419,
    "min": 0
  },
  "Pima Indians Diabetes": {
    "max": 0.7987,
    "min": 0
  }
}